setup.py
WeixunSDKFrs.egg-info/PKG-INFO
WeixunSDKFrs.egg-info/SOURCES.txt
WeixunSDKFrs.egg-info/dependency_links.txt
WeixunSDKFrs.egg-info/top_level.txt
weixunsdkfrs/__init__.py
weixunsdkfrs/request/__init__.py
weixunsdkfrs/request/v20170209/__init__.py