Metadata-Version: 1.1
Name: WeixunSDKFrs
Version: 0.1.20170213.1819
Summary: WeixunSDKFrs
Home-page: http://github.com/weixunsdkfrs
Author: Maple Liu
Author-email: maple.liu@microfastup.com
License: Apache License, Version 2.0
Platform: UNKNOWN
Classifier: Development Status :: 3 - Alpha
Classifier: Environment :: Web Environment
Classifier: Intended Audience :: Developers
Classifier: Operating System :: OS Independent
Classifier: Programming Language :: Python
